underpin/__init__.py
underpin/__main__.py
underpin/ai/model.py
underpin/config.py
underpin/pipeline/__init__.py
underpin/pipeline/default.py
underpin/schema/ChangeSet.py
underpin/schema/__init__.py
underpin/schema/common.py
underpin/setup.py
underpin/templates/UnderpinTemplate.py
underpin/templates/__init__.py
underpin/templates/template_containers.py
underpin/templates/template_yaml.py
underpin/utils/__init__.py
underpin/utils/funcs.py
underpin/utils/git/GitContext.py
underpin/utils/git/__init__.py
underpin/utils/io/__init__.py
underpin-0.1.2.dist-info/METADATA
underpin-0.1.2.dist-info/WHEEL
underpin-0.1.2.dist-info/entry_points.txt
underpin-0.1.2.dist-info/RECORD
