Metadata-Version: 2.1
Name: underpin
Version: 0.1.2
Summary: tools for sending app modules to k8s infrastructure and managing app versions
License: MIT
Author: mr-saoirse
Author-email: amartey@gmail.com
Requires-Python: >=3.10,<4.0
Classifier: License :: OSI Approved :: MIT License
Classifier: Programming Language :: Python :: 3
Classifier: Programming Language :: Python :: 3.10
Classifier: Programming Language :: Python :: 3.11
Requires-Dist: loguru (>=0.7.0,<0.8.0)
Requires-Dist: typer[all] (>=0.9.0,<0.10.0)
